py_hexagonal_arch/__init__.py
py_hexagonal_arch/adapters/__init__.py
py_hexagonal_arch/adapters/caches/__init__.py
py_hexagonal_arch/adapters/caches/base.py
py_hexagonal_arch/adapters/caches/user.py
py_hexagonal_arch/adapters/events/__init__.py
py_hexagonal_arch/adapters/events/base.py
py_hexagonal_arch/adapters/events/base_new.py
py_hexagonal_arch/adapters/events/kafka.py
py_hexagonal_arch/adapters/events/kinesis.py
py_hexagonal_arch/adapters/events/memory.py
py_hexagonal_arch/adapters/events/pubsub.py
py_hexagonal_arch/adapters/events/rabbitmq.py
py_hexagonal_arch/adapters/events/user.py
py_hexagonal_arch/adapters/repositories/__init__.py
py_hexagonal_arch/adapters/repositories/base.py
py_hexagonal_arch/adapters/repositories/user.py
py_hexagonal_arch/adapters/routers/__init__.py
py_hexagonal_arch/adapters/routers/base.py
py_hexagonal_arch/adapters/routers/user.py
py_hexagonal_arch/config/__init__.py
py_hexagonal_arch/config/settings.py
py_hexagonal_arch/controllers/__init__.py
py_hexagonal_arch/controllers/base.py
py_hexagonal_arch/controllers/user.py
py_hexagonal_arch/models/__init__.py
py_hexagonal_arch/models/base.py
py_hexagonal_arch/models/user.py
py_hexagonal_arch/ports/__init__.py
py_hexagonal_arch/ports/cache.py
py_hexagonal_arch/ports/event.py
py_hexagonal_arch/ports/repository.py
py_hexagonal_arch/ports/router.py
py_hexagonal_arch/schemas/__init__.py
py_hexagonal_arch/schemas/base.py
py_hexagonal_arch/schemas/user.py
py_hexagonal_arch-1.0.3.dist-info/licenses/LICENSE
py_hexagonal_arch-1.0.3.dist-info/METADATA
py_hexagonal_arch-1.0.3.dist-info/WHEEL
py_hexagonal_arch-1.0.3.dist-info/top_level.txt
py_hexagonal_arch-1.0.3.dist-info/RECORD
