Metadata-Version: 2.4
Name: py-hexagonal-arch
Version: 1.0.3
Summary: A comprehensive Python framework implementing Hexagonal Architecture with multi-framework, multi-database, and multi-messaging support
Author-email: Alberto Sanmartin Martinez <albertosanmartinmartinez@gmail.com>
Maintainer-email: Alberto Sanmartin Martinez <albertosanmartinmartinez@gmail.com>
License-Expression: MIT
Project-URL: Homepage, https://github.com/AlbertoSanmartinMartinez/py-hexagonal-arch
Project-URL: Documentation, https://github.com/AlbertoSanmartinMartinez/py-hexagonal-arch
Project-URL: Repository, https://github.com/AlbertoSanmartinMartinez/py-hexagonal-arch
Keywords: hexagonal-architecture,clean-architecture,ports-adapters,fastapi,flask,tornado,sqlalchemy,postgresql,mysql,redis,kafka,microservices,async,framework
Classifier: Development Status :: 4 - Beta
Classifier: Intended Audience :: Developers
Classifier: Topic :: Software Development :: Libraries :: Python Modules
Classifier: Topic :: Software Development :: Libraries :: Application Frameworks
Classifier: Programming Language :: Python :: 3
Classifier: Programming Language :: Python :: 3.8
Classifier: Programming Language :: Python :: 3.9
Classifier: Programming Language :: Python :: 3.10
Classifier: Programming Language :: Python :: 3.11
Classifier: Programming Language :: Python :: 3.12
Classifier: Operating System :: OS Independent
Classifier: Framework :: FastAPI
Classifier: Framework :: Flask
Classifier: Topic :: Database
Classifier: Topic :: Internet :: WWW/HTTP :: HTTP Servers
Classifier: Topic :: System :: Distributed Computing
Requires-Python: >=3.8
License-File: LICENSE
Requires-Dist: pydantic>=2.0.0
Requires-Dist: sqlalchemy[asyncio]>=2.0.0
Provides-Extra: fastapi
Requires-Dist: fastapi>=0.100.0; extra == "fastapi"
Requires-Dist: uvicorn[standard]>=0.20.0; extra == "fastapi"
Provides-Extra: flask
Requires-Dist: flask>=2.3.0; extra == "flask"
Requires-Dist: flask-cors>=4.0.0; extra == "flask"
Provides-Extra: tornado
Requires-Dist: tornado>=6.3.0; extra == "tornado"
Provides-Extra: postgresql
Requires-Dist: asyncpg>=0.28.0; extra == "postgresql"
Provides-Extra: mysql
Requires-Dist: aiomysql>=0.2.0; extra == "mysql"
Provides-Extra: mariadb
Requires-Dist: aiomysql>=0.2.0; extra == "mariadb"
Provides-Extra: sqlserver
Requires-Dist: aioodbc>=0.4.0; extra == "sqlserver"
Provides-Extra: oracle
Requires-Dist: cx_oracle_async>=0.3.0; extra == "oracle"
Provides-Extra: redis
Requires-Dist: redis[hiredis]>=4.5.0; extra == "redis"
Requires-Dist: aioredis>=2.0.0; extra == "redis"
Provides-Extra: memcache
Requires-Dist: aiomcache>=0.7.0; extra == "memcache"
Provides-Extra: kafka
Requires-Dist: aiokafka>=0.8.0; extra == "kafka"
Provides-Extra: rabbitmq
Requires-Dist: aio-pika>=9.0.0; extra == "rabbitmq"
Provides-Extra: kinesis
Requires-Dist: aioboto3>=11.0.0; extra == "kinesis"
Requires-Dist: boto3>=1.26.0; extra == "kinesis"
Provides-Extra: pubsub
Requires-Dist: google-cloud-pubsub>=2.18.0; extra == "pubsub"
Provides-Extra: dev
Requires-Dist: pytest>=7.4.0; extra == "dev"
Requires-Dist: pytest-asyncio>=0.21.0; extra == "dev"
Requires-Dist: pytest-cov>=4.1.0; extra == "dev"
Requires-Dist: black>=23.7.0; extra == "dev"
Requires-Dist: isort>=5.12.0; extra == "dev"
Requires-Dist: flake8>=6.0.0; extra == "dev"
Requires-Dist: mypy>=1.5.0; extra == "dev"
Requires-Dist: pre-commit>=3.4.0; extra == "dev"
Provides-Extra: docs
Requires-Dist: mkdocs>=1.5.0; extra == "docs"
Requires-Dist: mkdocs-material>=9.2.0; extra == "docs"
Requires-Dist: mkdocs-mermaid2-plugin>=1.1.0; extra == "docs"
Provides-Extra: web
Requires-Dist: fastapi>=0.100.0; extra == "web"
Requires-Dist: uvicorn[standard]>=0.20.0; extra == "web"
Provides-Extra: database
Requires-Dist: asyncpg>=0.28.0; extra == "database"
Provides-Extra: all
Requires-Dist: fastapi>=0.100.0; extra == "all"
Requires-Dist: uvicorn[standard]>=0.20.0; extra == "all"
Requires-Dist: flask>=2.3.0; extra == "all"
Requires-Dist: flask-cors>=4.0.0; extra == "all"
Requires-Dist: tornado>=6.3.0; extra == "all"
Requires-Dist: asyncpg>=0.28.0; extra == "all"
Requires-Dist: aiomysql>=0.2.0; extra == "all"
Requires-Dist: aioodbc>=0.4.0; extra == "all"
Requires-Dist: cx_oracle_async>=0.3.0; extra == "all"
Requires-Dist: redis[hiredis]>=4.5.0; extra == "all"
Requires-Dist: aioredis>=2.0.0; extra == "all"
Requires-Dist: aiomcache>=0.7.0; extra == "all"
Requires-Dist: aiokafka>=0.8.0; extra == "all"
Requires-Dist: aio-pika>=9.0.0; extra == "all"
Requires-Dist: aioboto3>=11.0.0; extra == "all"
Requires-Dist: boto3>=1.26.0; extra == "all"
Requires-Dist: google-cloud-pubsub>=2.18.0; extra == "all"
Dynamic: license-file
